kappybara/__init__.py
kappybara/algebra.py
kappybara/grammar.py
kappybara/kappa.lark
kappybara/mixture.py
kappybara/pattern.py
kappybara/rule.py
kappybara/system.py
kappybara/utils.py
kappybara-0.1.4.dist-info/METADATA
kappybara-0.1.4.dist-info/WHEEL
kappybara-0.1.4.dist-info/top_level.txt
kappybara-0.1.4.dist-info/RECORD
