Metadata-Version: 2.4
Name: kappybara
Version: 0.1.4
Summary: Work with Kappa rule-based models in Python
Project-URL: Homepage, https://kappybara.io
Project-URL: Documentation, https://kappybara.io/api/index.html
Project-URL: Repository, https://github.com/berkalpay/kappybara
Project-URL: Issues, https://github.com/berkalpay/kappybara/issues
Requires-Python: >=3.12
Requires-Dist: lark>=1.2.2
Requires-Dist: pandas>=2.0.0
Requires-Dist: matplotlib>=3.10.3
